src/hello.py
public_repo_testing-0.1.9.dist-info/METADATA
public_repo_testing-0.1.9.dist-info/WHEEL
public_repo_testing-0.1.9.dist-info/RECORD
