Metadata-Version: 2.4
Name: public-repo-testing
Version: 0.1.9
Summary: Add your description here
Requires-Python: >=3.12.4
